{
  "experiment": "experiment_1_fill_points",
  "scenario": "U",
  "mechanism": "hybrid",
  "method": "cg",
  "operation_mode": "sequential",
  "N": 75,
  "seed": 6,
  "objective": 151692.97109507243,
  "runtime": 15.808728799922392,
  "runtime_pricing": 0.0,
  "cg_iterations": 1,
  "internal_gap": 9.158001179228554e-09,
  "lp_lower_bound": 151692.97108118038,
  "n_columns_generated": 18310,
  "n_columns_added": 0,
  "num_pricing_calls": 0,
  "sp_share": 0.13333333333333333,
  "bs_share": 0.7733333333333333,
  "ae_share": 0.09333333333333334,
  "sp_utilization": 0.6366906474820144,
  "avg_stay_time": 15.142500103207489,
  "masking_rate": 0.0,
  "delay_cost": 2400.0,
  "energy_cost": 149292.97109507243,
  "success": true,
  "status": "ok",
  "lp_status": "Optimal",
  "ip_status": "Optimal",
  "trace_file": "results\\experiment_1_fill_points\\traces\\exp1_N75_seed6_scU_opsequential_cg.csv",
  "mode_assignments": [
    "brown",
    "battery",
    "battery",
    "battery",
    "battery",
    "battery",
    "shore",
    "battery",
    "battery",
    "battery",
    "battery",
    "shore",
    "battery",
    "battery",
    "battery",
    "brown",
    "battery",
    "battery",
    "brown",
    "shore",
    "shore",
    "battery",
    "battery",
    "brown",
    "battery",
    "battery",
    "battery",
    "battery",
    "battery",
    "battery",
    "battery",
    "battery",
    "shore",
    "battery",
    "battery",
    "battery",
    "battery",
    "battery",
    "battery",
    "battery",
    "battery",
    "battery",
    "battery",
    "shore",
    "brown",
    "battery",
    "battery",
    "battery",
    "battery",
    "battery",
    "battery",
    "shore",
    "battery",
    "shore",
    "battery",
    "battery",
    "brown",
    "battery",
    "battery",
    "battery",
    "battery",
    "battery",
    "battery",
    "battery",
    "battery",
    "battery",
    "shore",
    "battery",
    "battery",
    "battery",
    "battery",
    "battery",
    "battery",
    "shore",
    "brown"
  ],
  "start_times": [
    4.25,
    8.5,
    30.75,
    12.75,
    20.75,
    29.5,
    23.75,
    27.5,
    11.25,
    24.75,
    30.25,
    16.25,
    22.25,
    12.0,
    14.0,
    1.25,
    28.25,
    21.5,
    2.25,
    25.25,
    19.0,
    9.0,
    18.75,
    6.75,
    26.75,
    27.25,
    13.5,
    13.25,
    15.0,
    9.25,
    23.0,
    19.25,
    29.5,
    15.5,
    20.0,
    23.75,
    17.0,
    10.5,
    19.5,
    18.5,
    20.25,
    15.75,
    26.0,
    11.5,
    7.0,
    14.25,
    16.5,
    26.5,
    25.25,
    28.75,
    17.25,
    29.25,
    10.0,
    11.0,
    24.5,
    24.0,
    4.75,
    29.25,
    25.5,
    28.0,
    11.75,
    21.0,
    18.0,
    30.0,
    11.0,
    12.5,
    15.5,
    22.5,
    21.75,
    14.75,
    17.75,
    23.25,
    16.25,
    20.75,
    6.0
  ],
  "service_durations": [
    0.0,
    0.75,
    0.75,
    0.75,
    0.75,
    0.75,
    5.0,
    0.75,
    0.75,
    0.75,
    0.75,
    4.5,
    0.75,
    0.75,
    0.75,
    0.0,
    0.75,
    0.75,
    0.0,
    4.25,
    3.75,
    0.75,
    0.75,
    0.0,
    0.75,
    0.75,
    0.75,
    0.75,
    0.75,
    0.75,
    0.75,
    0.75,
    4.75,
    0.75,
    0.75,
    0.75,
    0.75,
    0.75,
    0.75,
    0.75,
    0.75,
    0.75,
    0.75,
    4.5,
    0.0,
    0.75,
    0.75,
    0.75,
    0.75,
    0.75,
    0.75,
    5.25,
    0.75,
    4.5,
    0.75,
    0.75,
    0.0,
    0.75,
    0.75,
    0.75,
    0.75,
    0.75,
    0.75,
    0.75,
    0.75,
    0.75,
    3.5,
    0.75,
    0.75,
    0.75,
    0.75,
    0.75,
    0.75,
    4.25,
    0.0
  ],
  "departure_times": [
    17.13510630271263,
    9.25,
    31.5,
    13.5,
    21.5,
    30.25,
    28.75,
    28.25,
    12.0,
    25.5,
    31.0,
    20.75,
    23.0,
    12.75,
    14.75,
    11.664178146937044,
    29.0,
    22.25,
    15.256800292139836,
    29.5,
    22.75,
    9.75,
    19.5,
    18.39708085427881,
    27.5,
    28.0,
    14.25,
    14.0,
    15.75,
    10.0,
    23.75,
    20.0,
    34.25,
    16.25,
    20.75,
    24.5,
    17.75,
    11.25,
    20.25,
    19.25,
    21.0,
    16.5,
    26.75,
    16.0,
    15.950585597393822,
    15.0,
    17.25,
    27.25,
    26.0,
    29.5,
    18.0,
    34.5,
    10.75,
    15.5,
    25.25,
    24.75,
    11.4901309250546,
    30.0,
    26.25,
    28.75,
    12.5,
    21.75,
    18.75,
    30.75,
    11.75,
    13.25,
    19.0,
    23.25,
    22.5,
    15.5,
    18.5,
    24.0,
    17.0,
    25.0,
    13.788474813633094
  ],
  "instance_audit": {
    "ship_type_counts": {
      "A": 13,
      "B": 38,
      "C": 9,
      "D": 15
    },
    "ship_type_ratios": {
      "A": 0.1733,
      "B": 0.5067,
      "C": 0.12,
      "D": 0.2
    },
    "arrival_time_range": [
      0.33389632971957006,
      7.967777281819468
    ],
    "cargo_time_range": [
      6.525410202807315,
      23.748472411149553
    ],
    "deadline_range": [
      10.74990688412388,
      34.53274213329635
    ],
    "energy_range": [
      3018.8067924856805,
      7874.390800530789
    ],
    "shore_compatible_ratio": 0.88
  }
}