{
  "config_name": "loose",
  "slack_low": 2.0,
  "slack_high": 6.0,
  "slack_mean": 4.0,
  "N": 100,
  "scenario": "U",
  "method": "cg",
  "operation_mode": "simops",
  "seed": 9,
  "delta": 1.5,
  "objective": 182111.37107415366,
  "runtime": 22.1387953000376,
  "cg_iterations": 1,
  "internal_gap": 0.0,
  "lp_lower_bound": 182111.37107415372,
  "sp_share": 0.15,
  "bs_share": 0.85,
  "ae_share": 0.0,
  "sp_utilization": 0.9928571428571429,
  "avg_stay_time": 15.48711156086987,
  "masking_rate": 0.49058945887278715,
  "delay_cost": 0.0,
  "delay_cost_pct": 0.0,
  "energy_cost": 182111.37107415366,
  "n_delayed_vessels": 0,
  "max_delay": 0.0,
  "avg_delay_of_delayed": 0.0,
  "n_mode_switches_vs_baseline": 9,
  "n_start_time_shifts": 86,
  "feasibility_margin": 0.0,
  "success": true,
  "status": "ok",
  "lp_status": "Optimal",
  "ip_status": "Optimal",
  "trace_file": "results\\experiment_2_tight_deadline\\traces\\exp2_loose_N100_seed9_delta1.5_cg.csv",
  "mode_assignments": [
    "battery",
    "battery",
    "battery",
    "battery",
    "battery",
    "battery",
    "battery",
    "battery",
    "battery",
    "shore",
    "battery",
    "battery",
    "battery",
    "battery",
    "battery",
    "battery",
    "shore",
    "battery",
    "battery",
    "battery",
    "battery",
    "battery",
    "battery",
    "battery",
    "battery",
    "shore",
    "battery",
    "battery",
    "battery",
    "battery",
    "battery",
    "battery",
    "battery",
    "battery",
    "battery",
    "battery",
    "battery",
    "battery",
    "battery",
    "battery",
    "battery",
    "battery",
    "battery",
    "battery",
    "battery",
    "battery",
    "battery",
    "battery",
    "battery",
    "shore",
    "battery",
    "battery",
    "battery",
    "shore",
    "battery",
    "battery",
    "battery",
    "battery",
    "battery",
    "battery",
    "battery",
    "battery",
    "shore",
    "battery",
    "battery",
    "shore",
    "battery",
    "battery",
    "battery",
    "battery",
    "battery",
    "battery",
    "battery",
    "battery",
    "battery",
    "shore",
    "battery",
    "battery",
    "battery",
    "shore",
    "battery",
    "battery",
    "battery",
    "battery",
    "shore",
    "battery",
    "battery",
    "shore",
    "battery",
    "battery",
    "battery",
    "battery",
    "battery",
    "battery",
    "shore",
    "shore",
    "battery",
    "battery",
    "shore",
    "shore"
  ],
  "start_times": [
    15.25,
    3.75,
    0.0,
    19.75,
    24.25,
    9.25,
    11.25,
    6.25,
    1.5,
    4.25,
    7.0,
    30.0,
    21.25,
    33.5,
    16.5,
    20.25,
    9.0,
    29.0,
    21.75,
    22.75,
    10.75,
    6.75,
    13.0,
    15.0,
    18.0,
    4.5,
    31.25,
    8.5,
    4.0,
    24.75,
    8.25,
    2.25,
    26.25,
    23.5,
    6.0,
    0.75,
    3.0,
    19.0,
    11.5,
    10.0,
    17.5,
    16.0,
    15.75,
    20.5,
    9.0,
    25.5,
    4.75,
    3.25,
    31.0,
    13.0,
    9.75,
    27.5,
    5.25,
    13.75,
    19.5,
    17.25,
    1.75,
    12.25,
    24.0,
    7.5,
    18.75,
    23.25,
    29.5,
    22.0,
    12.0,
    26.0,
    29.25,
    28.25,
    0.0,
    7.75,
    12.75,
    2.5,
    13.5,
    16.75,
    22.5,
    0.0,
    29.75,
    14.5,
    25.0,
    8.0,
    10.5,
    26.5,
    30.5,
    5.5,
    31.25,
    27.0,
    21.0,
    22.0,
    27.75,
    14.25,
    13.75,
    18.25,
    25.75,
    28.5,
    17.75,
    18.0,
    4.5,
    1.0,
    0.0,
    26.25
  ],
  "departure_times": [
    16.0,
    14.5,
    9.25,
    21.25,
    25.0,
    13.5,
    15.75,
    14.75,
    8.5,
    18.0,
    14.0,
    30.75,
    22.0,
    34.25,
    17.75,
    21.75,
    19.0,
    29.75,
    22.5,
    23.5,
    11.5,
    10.25,
    15.5,
    15.75,
    18.75,
    13.75,
    32.0,
    16.0,
    8.75,
    25.5,
    9.0,
    8.25,
    27.0,
    24.25,
    12.25,
    10.5,
    10.75,
    19.75,
    21.25,
    12.0,
    18.25,
    16.75,
    22.0,
    21.25,
    13.0,
    26.25,
    11.25,
    8.0,
    31.75,
    17.75,
    20.5,
    28.25,
    11.75,
    18.0,
    20.75,
    18.0,
    10.0,
    21.0,
    24.75,
    18.0,
    19.5,
    24.0,
    34.5,
    22.75,
    12.75,
    29.5,
    30.0,
    29.0,
    10.0,
    17.75,
    13.5,
    9.75,
    24.5,
    17.5,
    23.25,
    7.5,
    30.5,
    15.25,
    25.75,
    13.0,
    13.25,
    27.25,
    31.25,
    12.25,
    35.0,
    27.75,
    21.75,
    26.0,
    28.5,
    17.5,
    16.25,
    19.0,
    26.5,
    29.25,
    22.0,
    26.25,
    22.75,
    15.0,
    21.5,
    31.25
  ],
  "arrival_times": [
    4.8027916909400545,
    3.610132237290678,
    0.0,
    0.9090954854090894,
    2.716272601921003,
    4.979884503179967,
    4.659231968799622,
    4.130325253797303,
    1.312895453768162,
    2.095919571809994,
    5.29909651448088,
    3.2220898685846553,
    5.288226667068342,
    5.039173082546252,
    7.288292377992168,
    6.385017966362952,
    4.70964844638174,
    7.781415792180958,
    0.28768854837696156,
    7.089144920999079,
    2.541655781514809,
    3.560728191586949,
    7.502244079280596,
    6.331933970419479,
    6.363787049219416,
    4.264085582656075,
    3.825232156949394,
    5.490586747101027,
    1.9526236885465194,
    4.834072648078752,
    1.93176832617437,
    0.20941223509674267,
    0.7232261355574154,
    5.902718434477781,
    4.860250103087291,
    0.6793561926351823,
    2.6514843816258282,
    5.851601560371685,
    0.6256083047607148,
    3.9389808503670003,
    2.3772998728229604,
    5.864128880780317,
    2.274084609490325,
    4.011382713181559,
    4.000860398250045,
    7.094897781550422,
    4.524405038769656,
    0.3357232224828409,
    4.10318840252308,
    1.6882773310823005,
    4.868452630470505,
    0.6756594480006601,
    4.48384077098743,
    4.675589848576046,
    3.3548520882766617,
    7.581794114416212,
    1.5985341824521822,
    6.220229028120729,
    3.6544913435556277,
    2.5229240722779083,
    5.419727427268354,
    3.920902025685253,
    7.286677643779804,
    7.952291473886696,
    1.1361986997890106,
    1.810853357337499,
    4.558152993741812,
    6.4143964033912235,
    0.0,
    7.6614425270165345,
    1.6776585741746426,
    2.2774590057011386,
    2.4977596044797563,
    6.156905687619753,
    3.0401511955751763,
    0.0,
    4.339068789783598,
    6.086962629788366,
    3.1140380839907196,
    2.7219756150336725,
    4.569351824191548,
    6.706227440984126,
    7.06646746774122,
    4.200211500120017,
    7.066801065689254,
    0.9427125063447104,
    4.831587220137787,
    5.975599267634456,
    7.485012492354551,
    6.416230516044136,
    4.513133835391572,
    7.363310461558966,
    7.763383707948082,
    8.145277978943142,
    2.7487123636592625,
    7.476231334149965,
    2.046341195813424,
    0.9070053192605245,
    0.0,
    6.948007090644184
  ],
  "deadlines": [
    16.278941744007998,
    18.03155997339948,
    12.817225699233202,
    25.06724167785369,
    25.320604062199912,
    15.257719876058253,
    18.03092694854535,
    20.19915379496534,
    12.078952504833264,
    24.66773497067655,
    16.258926327452144,
    30.580574437113995,
    23.763806221469853,
    34.12895754738536,
    21.139879678398135,
    26.114743616835234,
    20.903653559090728,
    29.73398960242554,
    25.139888570675303,
    23.568841714452446,
    14.566654169298921,
    14.03010933984222,
    18.62599608319287,
    17.471048176215145,
    20.24432894800974,
    14.343846210672213,
    31.793753264568707,
    17.704806942838218,
    12.589300840771951,
    26.21204772206638,
    11.108836345091813,
    11.458186908750283,
    26.84643621399057,
    26.22651785059422,
    13.803847570857393,
    12.190491248782816,
    13.842518418042195,
    20.15391169235145,
    25.589133375190993,
    13.593368821625102,
    22.516436396191004,
    17.316900057237095,
    23.787281575521753,
    22.136552252804883,
    15.079817974504381,
    26.182244054969672,
    14.464123307475194,
    11.505807434053342,
    31.50461094824538,
    20.327542315021983,
    23.169973379660217,
    28.21959455630357,
    15.008267594435104,
    18.9154372597513,
    25.686803483342985,
    18.572797033116995,
    13.748028607190458,
    24.6459702810154,
    24.945332264735917,
    21.251412277549733,
    23.264762826682404,
    23.88831651769128,
    34.32108306329565,
    23.44736339336068,
    13.887602986710132,
    29.813845835454416,
    29.96013379435432,
    29.496550220734555,
    15.480515995477782,
    22.347272377547057,
    16.105836653900788,
    13.416843627827436,
    27.051018328262504,
    17.384266448444386,
    24.216965977872693,
    12.991115945844468,
    30.665395562564267,
    19.154028003253632,
    25.5200169704069,
    14.725035065320553,
    17.266170668342966,
    27.242351999099753,
    32.65705713823137,
    15.729049930324262,
    34.94589756458426,
    28.14551575467995,
    23.00480129093842,
    25.896988301046008,
    28.316540911899693,
    20.035521992645034,
    20.17948066052797,
    20.920921856442266,
    26.919308620334775,
    29.131565408688292,
    25.741704543473553,
    26.042138380767135,
    26.033689951819078,
    18.40939449723489,
    26.49213099382593,
    32.92788117192726
  ]
}